tests/__init__.py
tests/settings.py
tests/urls.py
tests/test/__init__.py
tests/test/tests/__init__.py
tests/test/tests/factories.py
tests/test/tests/test_channels_email.py
tests/test/tests/test_channels_sms.py
tests/test/tests/test_command.py
tests/test/tests/test_decorator.py
tests/test/tests/test_lock.py
tests/test/tests/test_models.py
tests/test/tests/test_package.py
tests/test/tests/test_tasks.py
transmissions/__init__.py
transmissions/admin.py
transmissions/exceptions.py
transmissions/lock.py
transmissions/models.py
transmissions/tasks.py
transmissions/trigger.py
transmissions/views.py
transmissions/channels/__init__.py
transmissions/channels/email.py
transmissions/channels/sms.py
transmissions/management/__init__.py
transmissions/management/commands/__init__.py
transmissions/management/commands/rename_from_dt.py
transmissions/management/commands/retry_failed_notifications.py
transmissions/migrations/0001_initial.py
transmissions/migrations/0002_auto_20150105_1523.py
transmissions/migrations/0003_auto_20151221_1716.py
transmissions/migrations/__init__.py
transmissions-0.1.7.1.dist-info/DESCRIPTION.rst
transmissions-0.1.7.1.dist-info/METADATA
transmissions-0.1.7.1.dist-info/RECORD
transmissions-0.1.7.1.dist-info/WHEEL
transmissions-0.1.7.1.dist-info/metadata.json
transmissions-0.1.7.1.dist-info/pbr.json
transmissions-0.1.7.1.dist-info/top_level.txt
