Metadata-Version: 2.0
Name: transmissions
Version: 0.1.7.1
Summary: Transmissions is a Django application that channels all user notifications via email, sms, push notifcations, etc.
Home-page: https://github.com/makingspace/transmissions
Author: MakeSpace Labs, Inc.
Author-email: nicolas.grasset@makespace.com
License: Simplified BSD
Platform: UNKNOWN
Classifier: Framework :: Django
Classifier: Intended Audience :: Developers
Classifier: License :: OSI Approved :: BSD License
Classifier: Operating System :: OS Independent
Classifier: Programming Language :: Python
Classifier: Topic :: Database
Requires-Dist: Django (>=1.7)
Requires-Dist: celery (>=2.2.7)
Requires-Dist: django-enumfield
Requires-Dist: django-extensions
Requires-Dist: shortuuid
